quienesquien/__init__.py
quienesquien/client.py
quienesquien/enums.py
quienesquien/exc.py
quienesquien/person.py
quienesquien/version.py
quienesquien-1.0.4.dist-info/licenses/LICENSE
tests/__init__.py
tests/conftest.py
tests/test_client.py
tests/test_person.py
quienesquien-1.0.4.dist-info/METADATA
quienesquien-1.0.4.dist-info/WHEEL
quienesquien-1.0.4.dist-info/top_level.txt
quienesquien-1.0.4.dist-info/RECORD
